entity_linker_client/__init__.py
entity_linker_client/_version.py
entity_linker_client/config.py
entity_linker_client/http_client.py
entity_linker_client/linker_client.py
entity_linker_client/models.py
entity_linker_client/py.typed
entity_linker_client/utils.py
entity_linker_client-1.1.1.dist-info/licenses/LICENSE
entity_linker_client-1.1.1.dist-info/METADATA
entity_linker_client-1.1.1.dist-info/WHEEL
entity_linker_client-1.1.1.dist-info/top_level.txt
entity_linker_client-1.1.1.dist-info/RECORD
