Metadata-Version: 2.4
Name: entity-linker-client
Version: 1.1.1
Summary: A Python client for the Entity Linker service - intelligent entity matching and linking
Author-email: Godel Backend Team <support@godel-ai.com>
Maintainer-email: Godel Backend Team <support@godel-ai.com>
License-Expression: MIT
Project-URL: Homepage, https://github.com/godel-ai/entity-linker-client
Project-URL: Documentation, https://github.com/godel-ai/entity-linker-client#readme
Project-URL: Repository, https://github.com/godel-ai/entity-linker-client
Project-URL: Issues, https://github.com/godel-ai/entity-linker-client/issues
Project-URL: Changelog, https://github.com/godel-ai/entity-linker-client/blob/main/CHANGELOG.md
Keywords: entity-linking,data-matching,nlp,entity-resolution,record-linkage,fuzzy-matching,semantic-similarity
Classifier: Development Status :: 5 - Production/Stable
Classifier: Intended Audience :: Developers
Classifier: Intended Audience :: Science/Research
Classifier: Operating System :: OS Independent
Classifier: Programming Language :: Python :: 3
Classifier: Programming Language :: Python :: 3.8
Classifier: Programming Language :: Python :: 3.9
Classifier: Programming Language :: Python :: 3.10
Classifier: Programming Language :: Python :: 3.11
Classifier: Programming Language :: Python :: 3.12
Classifier: Topic :: Scientific/Engineering :: Artificial Intelligence
Classifier: Topic :: Software Development :: Libraries :: Python Modules
Classifier: Topic :: Text Processing :: Linguistic
Requires-Python: >=3.8
License-File: LICENSE
Requires-Dist: httpx>=0.24.0
Requires-Dist: python-dotenv>=0.19.0
Provides-Extra: dev
Requires-Dist: pytest>=7.0.0; extra == "dev"
Requires-Dist: pytest-cov; extra == "dev"
Requires-Dist: black; extra == "dev"
Requires-Dist: isort; extra == "dev"
Requires-Dist: flake8; extra == "dev"
Requires-Dist: mypy; extra == "dev"
Requires-Dist: build; extra == "dev"
Requires-Dist: twine; extra == "dev"
Requires-Dist: notebook; extra == "dev"
Requires-Dist: jupyter; extra == "dev"
Dynamic: license-file
